{
  "slug": "shane-jones",
  "name": "Shane Jones",
  "researchStatus": "done",
  "lastUpdated": "2026-01-31T11:03:23.655Z",
  "postalAddress": {
    "status": "found",
    "value": "Freepost Parliament, Private Bag 18 888, Parliament Buildings, Wellington 6160",
    "source": "https://www.haveyoursay.org.nz/mp/shane-jones",
    "notes": "Postal address listed on Have Your Say profile"
  },
  "donationMethod": {
    "status": "not-found",
    "method": "party-channel",
    "url": "https://www.nzfirst.nz/donate",
    "bankAccount": null,
    "details": null,
    "notes": "NZ First donation page exists; no MP-specific donation method found"
  },
  "aiInvolvement": {
    "status": "checked",
    "level": "none",
    "evidence": [],
    "notes": "Scanned HaveYourSay summary for AI keywords; none found (parliament site blocked by captcha)"
  },
  "personalizationNotes": null,
  "sourcesChecked": [
    {
      "source": "https://www.haveyoursay.org.nz/mp/shane-jones",
      "checked": true,
      "foundUseful": true,
      "notes": "Found Freepost Parliament / Private Bag 18 888 postal address"
    },
    {
      "source": "https://www.nzfirst.nz/shane-jones",
      "checked": true,
      "foundUseful": false,
      "notes": "Profile page has a DONATE link but it goes to party donate page"
    },
    {
      "source": "https://www.nzfirst.nz/donate",
      "checked": true,
      "foundUseful": true,
      "notes": "NZ First party donation page (online form); no MP-specific donation method listed"
    },
    {
      "source": "https://www.haveyoursay.org.nz/mp/shane-jones",
      "checked": true,
      "foundUseful": false,
      "notes": "AI keyword scan (none found)"
    }
  ]
}